sparticles/__init__.py
sparticles/dataset.py
sparticles/models.py
sparticles/train.py
sparticles/transforms.py
sparticles/utils.py
sparticles/visualize.py
sparticles-0.0.4.5.dist-info/LICENSE
sparticles-0.0.4.5.dist-info/METADATA
sparticles-0.0.4.5.dist-info/WHEEL
sparticles-0.0.4.5.dist-info/top_level.txt
sparticles-0.0.4.5.dist-info/RECORD
