Metadata-Version: 2.1
Name: sparticles
Version: 0.0.4.5
Summary: A package to manipulate particle collisions
Author-email: Alessio Devoto <devoto.alessio@gmail.com>
Project-URL: Homepage, https://github.com/alessiodevoto/sparticles
Project-URL: Bug Tracker, https://github.com/alessiodevoto/sparticles/issues
Classifier: Programming Language :: Python :: 3
Classifier: License :: OSI Approved :: MIT License
Classifier: Operating System :: OS Independent
Requires-Python: >=3.7
License-File: LICENSE
Requires-Dist: pandas >=1.5.0
Requires-Dist: plotly >=5.10.0
Requires-Dist: kaleido >=0.2.1
Requires-Dist: torch-geometric >=2.0.1
